llm4ad/__init__.py
llm4ad/gui.py
llm4ad/base/__init__.py
llm4ad/base/code.py
llm4ad/base/evaluate.py
llm4ad/base/modify_code.py
llm4ad/base/sample.py
llm4ad/method/__init__.py
llm4ad/method/eoh/__init__.py
llm4ad/method/eoh/eoh.py
llm4ad/method/eoh/population.py
llm4ad/method/eoh/profiler.py
llm4ad/method/eoh/prompt.py
llm4ad/method/eoh/resume.py
llm4ad/method/eoh/sampler.py
llm4ad/method/funsearch/__init__.py
llm4ad/method/funsearch/config.py
llm4ad/method/funsearch/funsearch.py
llm4ad/method/funsearch/profiler.py
llm4ad/method/funsearch/programs_database.py
llm4ad/method/funsearch/resume.py
llm4ad/method/hillclimb/__init__.py
llm4ad/method/hillclimb/hillclimb.py
llm4ad/method/hillclimb/profiler.py
llm4ad/method/hillclimb/resume.py
llm4ad/method/meoh/__init__.py
llm4ad/method/meoh/meoh.py
llm4ad/method/meoh/population.py
llm4ad/method/meoh/profiler.py
llm4ad/method/meoh/prompt.py
llm4ad/method/meoh/resume.py
llm4ad/method/meoh/sampler.py
llm4ad/method/moead/__init__.py
llm4ad/method/moead/moead.py
llm4ad/method/moead/population.py
llm4ad/method/moead/profiler.py
llm4ad/method/moead/prompt.py
llm4ad/method/moead/resume.py
llm4ad/method/moead/sampler.py
llm4ad/method/nsga2/__init__.py
llm4ad/method/nsga2/nsga2.py
llm4ad/method/nsga2/population.py
llm4ad/method/nsga2/profiler.py
llm4ad/method/nsga2/prompt.py
llm4ad/method/nsga2/resume.py
llm4ad/method/nsga2/sampler.py
llm4ad/method/randsample/__init__.py
llm4ad/method/randsample/profiler.py
llm4ad/method/randsample/randsample.py
llm4ad/method/randsample/resume.py
llm4ad/task/__init__.py
llm4ad/task/machine_learning/__init__.py
llm4ad/task/machine_learning/acrobot/__init__.py
llm4ad/task/machine_learning/acrobot/evaluation.py
llm4ad/task/machine_learning/acrobot/template.py
llm4ad/task/machine_learning/acrobot/test.py
llm4ad/task/machine_learning/car_mountain/__init__.py
llm4ad/task/machine_learning/car_mountain/evaluation.py
llm4ad/task/machine_learning/car_mountain/q-learning.py
llm4ad-1.11.dist-info/LICENSE
llm4ad-1.11.dist-info/METADATA
llm4ad-1.11.dist-info/WHEEL
llm4ad-1.11.dist-info/top_level.txt
llm4ad-1.11.dist-info/RECORD
